Metadata-Version: 2.1
Name: pythonTvaritha
Version: 0.0.1
Summary: this is a trial package used for calculation.
Home-page: 
Author: D.SaiTvaritha
Author-email: tvaritha999@gmail.com
License: MIT
Platform: UNKNOWN
License-File: LICENCE.txt
